assignment/imt2019512_Q1.v
module state_machine(inp , clk , reset , out) ; 
	input inp , clk , reset ; 
	output reg out ; 

	reg [2:0] state  ; 
	parameter A = 2'b00 , B = 2'b01 , C = 2'b10 ;  

	always @(posedge clk)
		begin
			if(!reset)
				case(state) 
					A : 	  if(inp == 0) 
							  	begin
							  		state <= B ; 
							  		out <= 0 ;
							  	end   
							  else
							  	begin
							  		state <= C ; 
							  		out <= 0 ;  
							  	end

					B : 	 if(inp == 0) 
							  	begin
							  		state <= B ; 
							  		out <= 0 ;
							  	end   
							  else
							  	begin
							  		state <= C ; 
							  		out <= 1 ;  
							  	end
					
					C : 	  if(inp == 0) 
							  	begin
							  		state <= B ; 
							  		out <= 1 ;
							  	end   
							  else
							  	begin
							  		state <= C ; 
							  		out <= 0 ;  
							  	end
					
					default : begin
								state <= A ; 
								out <= 0 ; 
							  end 
				endcase

			else 
				begin	
					state <=  A ; 
					out <= 0 ; 
				end 
		end
endmodule

assignment/imt2019512_Q1_tb.v
`timescale 1ns/1ps 

module Q1_tb ; 
	reg inp , rst ; 
	reg clk ; 
	output out ; 

	state_machine DUT(.inp(inp) , .clk(clk) , .reset(rst) , .out(out)) ; 

	initial 
		clk =0 ;

	always #10 clk = ~clk ;  

	initial 
		begin
			$dumpfile ("Q1_out.vcd"); 
			$dumpvars(0, Q1_tb);
			$monitor($time , " clk = %b , rst = %b , inp = %b , out = %b " , clk , rst , inp , out) ; 

			#20 inp = 0 ; rst = 0 ; 
			#20 inp = 0 ;
			#20 inp = 1 ; 
			#20 inp = 1 ;  
			#20 inp = 0 ; 
			#20 inp = 1 ; rst = 1 ; 
			#10 inp = 1 ; 

			#10 $finish ; 
		end 
endmodule

assignment/Q1_out.vcd
$date
	Wed Apr 29 18:37:06 2020
$end
$version
	Icarus Verilog
$end
$timescale
	1ps
$end
$scope module Q1_tb $end
$var wire 1 ! out $end
$var reg 1 " clk $end
$var reg 1 # inp $end
$var reg 1 $ rst $end
$scope module DUT $end
$var wire 1 " clk $end
$var wire 1 # inp $end
$var wire 1 $ reset $end
$var reg 1 ! out $end
$var reg 3 % state [2:0] $end
$upscope $end
$upscope $end
$enddefinitions $end
#0
$dumpvars
bx %
x$
x#
0"
x!
$end
#10000
0!
b0 %
1"
#20000
0"
0$
0#
#30000
b1 %
1"
#40000
0"
#50000
1"
#60000
0"
1#
#70000
1!
b10 %
1"
#80000
0"
#90000
0!
1"
#100000
0"
0#
#110000
1!
b1 %
1"
#120000
0"
1$
1#
#130000
0!
b0 %
1"
