assignment/IMT2019512_TLC_FSM.v

module TLC(clock , TA , TB , lightA , lightB , cond , reset ) ; 
	input clock , cond , reset ; 
	input TA , TB  ; 
	output reg[1:0] lightA , lightB ; 
	reg [2:0] state ;
	reg delay , count_delay , count ; 

	parameter S0 = 3'b001 ,
			  S1 = 3'b010 ,
			  S2 = 3'b011 , 
			  S3 = 3'b100 ,
			  S4 = 3'b101 , 
			  S5 = 3'b110 ;

	parameter RED			= 2'b00 ,
			  YELLOW 		= 2'b01 , 
			  GREEN			= 2'b10 ;

	initial 
		state <= S0 ;

	always @(posedge clock)
	begin 
		if(!reset)
		 	case(state)
		 		S0 			: begin 
			 					  if(TA == 0 && cond == 1) state = S2 ;
			 					  else if (TA == 0) state = S1 ; 
			 					  else state = S0 ; 
			 					  lightA = GREEN ;
			 					  lightB = RED ;
			 				  end 

		 		S1 			: begin 
			 					  state = S4 ;
			 					  lightA = YELLOW 	; 
			 					  lightB = RED 	; 
			 				  end 

		 		S2 			: begin 
		 						delay = 1 ;
		 						if(count_delay == 1)
		 							state = S4 ;
		 						lightA = YELLOW	; 
		 						lightB = RED 	;
		 					  end 

		 		S3 			: begin 
			 					  state = S0 ; 
			 		  			  lightA = RED	; 
			 		  			  lightB = YELLOW ;
			 		  		  end 
			 		  		  	  	
		 		S4 			: begin 
			 					  if(TB == 0 && cond == 1) state = S5 ;
			 					  else if (TB == 0) state = S3 ; 
			 					  else state = S4 ; 
			 					  lightA = RED 	; 
			 					  lightB = GREEN ;
			 				  end 

		 		S5 			: begin 
		 						delay = 1 ;
		 						if(count_delay == 1)
		 							state = S0 ;
		 						lightA = RED ;
		 						lightB = YELLOW ;
		 					  end 	  

		 		default 	: state <= S0 ; 
		 	endcase 

		else
			state <= S0 ; 
	end 

	always @(posedge clock)
		begin 
			if(delay) 
				count <= count + 1 ; 
				if(count == 2)
					count_delay = 1 ;
					count <= 0  ; 
		end
endmodule 


`timescale 1ns/1ps 

module TLC_test ; 
	reg clock , cond , reset , count , TA , TB ;
	output [1:0] lightA , lightB ; 

	TLC test(clock , TA , TB , lightA , lightB , cond , reset ) ; 

	initial 
	begin 
		clock = 1'b0 ;
		reset = 1'b0 ;
		cond = 1'b0 ; 
	end  

	always #5 clock = ~clock ; 

	initial 
		begin
			$dumpfile ("TLC_out.vcd"); 
			$dumpvars(0, TLC_test);
			$monitor($time , " clock = %b , rst = %b , TA = %b ,  TB = %b , lightA = %2b  , lightB = %2b ", clock , reset , TA , TB , lightA , lightB) ; 

			#5 TA = 1 ;
			#20 TA = 0  ;
			#20 TB = 0 ; TA = 1 ;
			#20	cond = 1 ; TB = 1 ;
			#1 ;
			#20 TB = 0 ;TA = 1 ; 
			#20 $finish ; 
		end 
endmodule

assignment/TLC_out.vcd
$date
	Thu May 14 22:51:53 2020
$end
$version
	Icarus Verilog
$end
$timescale
	1ps
$end
$scope module TLC_test $end
$var wire 2 ! lightB [1:0] $end
$var wire 2 " lightA [1:0] $end
$var reg 1 # TA $end
$var reg 1 $ TB $end
$var reg 1 % clock $end
$var reg 1 & cond $end
$var reg 1 ' reset $end
$scope module test $end
$var wire 1 # TA $end
$var wire 1 $ TB $end
$var wire 1 % clock $end
$var wire 1 & cond $end
$var wire 1 ' reset $end
$var reg 1 ( count $end
$var reg 1 ) count_delay $end
$var reg 1 * delay $end
$var reg 2 + lightA [1:0] $end
$var reg 2 , lightB [1:0] $end
$var reg 3 - state [2:0] $end
$upscope $end
$upscope $end
$enddefinitions $end
#0
$dumpvars
b1 -
bx ,
bx +
x*
x)
x(
0'
0&
0%
x$
x#
bx "
bx !
$end
#5000
0(
b0 !
b0 ,
b10 "
b10 +
1#
1%
#10000
0%
#15000
1%
#20000
0%
#25000
b10 -
1%
0#
#30000
0%
#35000
b1 "
b1 +
b101 -
1%
#40000
0%
#45000
b10 !
b10 ,
b0 "
b0 +
b100 -
1%
1#
0$
#50000
0%
#55000
b1 !
b1 ,
b1 -
1%
#60000
0%
#65000
b0 !
b0 ,
b10 "
b10 +
1%
1$
1&
#70000
0%
#75000
1%
#80000
0%
#85000
1%
#86000
0$
