flip-flop_with_a_negative-edge_clock_and_synchronous_clear/flip-flop_with_a_negative-edge_clock_and_synchronous_clear.v
module flip_flop(clk , d, q, clr) ;
	input clk , d, clr; 
	output reg q; 

	always @(posedge clk )

	begin
		if(clr)
			q <= 1'b0 ;
		else
			q <= d; 

	end 
endmodule 

// for asynchronous use always @(posedge clk or posedge clr) .
// in testbench write similar thing for clr as clk .

flip-flop_with_a_negative-edge_clock_and_synchronous_clear/flip-flop_with_a_negative-edge_clock_and_synchronous_clear_tb.v
`timescale 1ns/1ps 

module testbench() ;
	reg in ; 
	reg clk ; 
	reg rst ; 
	output out ; 

	flip_flop dut(.d(in) , .clk(clk) , .q(out) , .clr(rst)) ; 

	initial begin 
		clk = 0 ; 
			forever #10 clk = ~clk ; 
	end 

	initial begin
		$dumpfile ("flip_flop_out.vcd"); 
		$dumpvars(0, testbench);
		$monitor($time , "  in = %b , clk = %b , rst = %b , out = %b " , in , clk , rst , out) ; 

		#20 in =0 ; rst = 0 ; 
		#20 in =1 ; 
		#20 in = 0 ; 
		#20 in = 1 ; rst =0 ; 
		#10 in = 1 ; rst = 1 ;

		#10 $finish ; 
	end 
endmodule

flip-flop_with_a_negative-edge_clock_and_synchronous_clear/flip_flop_out.vcd
$date
	Mon Apr 13 19:02:44 2020
$end
$version
	Icarus Verilog
$end
$timescale
	1ps
$end
$scope module testbench $end
$var wire 1 ! out $end
$var reg 1 " clk $end
$var reg 1 # in $end
$var reg 1 $ rst $end
$scope module dut $end
$var wire 1 " clk $end
$var wire 1 $ clr $end
$var wire 1 # d $end
$var reg 1 ! q $end
$upscope $end
$upscope $end
$enddefinitions $end
#0
$dumpvars
x$
x#
0"
x!
$end
#10000
1"
#20000
0"
0$
0#
#30000
0!
1"
#40000
0"
1#
#50000
1!
1"
#60000
0"
0#
#70000
0!
1"
#80000
0"
1#
#90000
1"
1$
